{"is_source_file": true, "format": "TypeScript", "description": "This file primarily re-exports the store and type definitions for the application's state management, acting as an index barrel for store-related exports.", "external_files": ["./index"], "external_methods": [], "published": ["store", "RootState", "AppDispatch"], "classes": [], "methods": [], "calls": [], "search-terms": ["store", "RootState", "AppDispatch", "index.tsx", "re-export", "state management", "TypeScript"], "state": 2, "file_id": 17, "knowledge_revision": 63, "git_revision": "6afdd3d461c90f1078d72856a655354a3eb9ad5c", "revision_history": [{"40": ""}, {"63": "6afdd3d461c90f1078d72856a655354a3eb9ad5c"}], "ctags": [], "hash": "a440fefe0a29045cbe3a1832f6f3f95a", "format-version": 4, "code-base-name": "FrontendWebApplication", "filename": "FrontendWebApplication/src/store/index.tsx"}